ara_log/__init__.py
ara_log/log.py
ara_log-1.0.0.dist-info/METADATA
ara_log-1.0.0.dist-info/WHEEL
ara_log-1.0.0.dist-info/top_level.txt
ara_log-1.0.0.dist-info/RECORD
