Metadata-Version: 2.4
Name: Ara_log
Version: 1.0.0
Summary: A simple, minimalistic python logger using the `logging` library as its basis
Author-email: HanamileH <hanamileh@gmail.com>
License-Expression: MIT
Project-URL: Homepage, https://github.com/hanamileh-DEV/Ara_log
Requires-Python: >=3.7
